{"otherData": {},"traceEvents":[{},{"cat":"function","dur":2155,"name":"void Vertex::Logger::Init(void)","ph":"X","pid":0,"tid":21092,"ts":171478500794.300},{"cat":"function","dur":118,"name":"void Vertex::WindowsWindow::SetVSync(bool)","ph":"X","pid":0,"tid":21092,"ts":171479485401.500},{"cat":"function","dur":982177,"name":"void Vertex::WindowsWindow::Init(const struct Vertex::WindowProps &)","ph":"X","pid":0,"tid":21092,"ts":171478503470.700},{"cat":"function","dur":982258,"name":"Vertex::WindowsWindow::WindowsWindow(const struct Vertex::WindowProps &)","ph":"X","pid":0,"tid":21092,"ts":171478503469.400},{"cat":"function","dur":982597,"name":"class Vertex::Window *Vertex::Window::Create(const struct Vertex::WindowProps &)","ph":"X","pid":0,"tid":21092,"ts":171478503465.700},{"cat":"function","dur":5087,"name":"void Vertex::Application::PushOverlay(class Vertex::Layer *)","ph":"X","pid":0,"tid":21092,"ts":171479622748.100},{"cat":"function","dur":1124585,"name":"Vertex::Application::Application(const class std::basic_string<char,struct std::char_traits<char>,class std::allocator<char> > &)","ph":"X","pid":0,"tid":21092,"ts":171478503445.600},{"cat":"function","dur":5465,"name":"void Vertex::EditorLayer::OnAttach(void)","ph":"X","pid":0,"tid":21092,"ts":171481102786.900},{"cat":"function","dur":5636,"name":"void Vertex::Application::PushLayer(class Vertex::Layer *)","ph":"X","pid":0,"tid":21092,"ts":171481102776.700}]}